json_assertion/__init__.py
json_assertion/py.typed
json_assertion/testing.py
json_assertion-1.1.0.dist-info/METADATA
json_assertion-1.1.0.dist-info/WHEEL
json_assertion-1.1.0.dist-info/licenses/LICENSE
json_assertion-1.1.0.dist-info/RECORD
